bc_pulse/__init__.py
bc_pulse/__main__.py
bc_pulse/checkKey.py
bc_pulse/pytransform.py
bc_pulse/cli/__init__.py
bc_pulse/cli/color.py
bc_pulse/cli/dialog_creator.py
bc_pulse/cli/feature_handler.py
bc_pulse/cli/file_dialog.py
bc_pulse/cli/main.py
bc_pulse/cli/save_management.py
bc_pulse/cli/server_cli.py
bc_pulse/cli/edits/__init__.py
bc_pulse/cli/edits/aku_realm.py
bc_pulse/cli/edits/basic_items.py
bc_pulse/cli/edits/cat_editor.py
bc_pulse/cli/edits/clear_tutorial.py
bc_pulse/cli/edits/enemy_editor.py
bc_pulse/cli/edits/fixes.py
bc_pulse/cli/edits/map.py
bc_pulse/cli/edits/rare_ticket_trade.py
bc_pulse/core/__init__.py
bc_pulse/core/country_code.py
bc_pulse/core/crypto.py
bc_pulse/core/game_version.py
bc_pulse/core/locale_handler.py
bc_pulse/core/log.py
bc_pulse/core/max_value_helper.py
bc_pulse/core/theme_handler.py
bc_pulse/core/game/__init__.py
bc_pulse/core/game/localizable.py
bc_pulse/core/game/battle/__init__.py
bc_pulse/core/game/battle/battle_items.py
bc_pulse/core/game/battle/cleared_slots.py
bc_pulse/core/game/battle/enemy.py
bc_pulse/core/game/battle/slots.py
bc_pulse/core/game/catbase/__init__.py
bc_pulse/core/game/catbase/beacon_base.py
bc_pulse/core/game/catbase/cat.py
bc_pulse/core/game/catbase/drop_chara.py
bc_pulse/core/game/catbase/gatya.py
bc_pulse/core/game/catbase/gatya_item.py
bc_pulse/core/game/catbase/item_pack.py
bc_pulse/core/game/catbase/login_bonuses.py
bc_pulse/core/game/catbase/matatabi.py
bc_pulse/core/game/catbase/medals.py
bc_pulse/core/game/catbase/mission.py
bc_pulse/core/game/catbase/my_sale.py
bc_pulse/core/game/catbase/nyanko_club.py
bc_pulse/core/game/catbase/officer_pass.py
bc_pulse/core/game/catbase/playtime.py
bc_pulse/core/game/catbase/powerup.py
bc_pulse/core/game/catbase/scheme_items.py
bc_pulse/core/game/catbase/special_skill.py
bc_pulse/core/game/catbase/stamp.py
bc_pulse/core/game/catbase/talent_orbs.py
bc_pulse/core/game/catbase/unlock_popups.py
bc_pulse/core/game/catbase/upgrade.py
bcsfeKORtest-3.0.0b9.dist-info/LICENSE
bcsfeKORtest-3.0.0b9.dist-info/METADATA
bcsfeKORtest-3.0.0b9.dist-info/WHEEL
bcsfeKORtest-3.0.0b9.dist-info/top_level.txt
bcsfeKORtest-3.0.0b9.dist-info/RECORD
